{
	"name": "Chile_Delete",
	"properties": {
		"linkedServiceName": {
			"referenceName": "DataLakePlatform",
			"type": "LinkedServiceReference"
		},
		"parameters": {
			"file": {
				"type": "string"
			},
			"zona": {
				"type": "string"
			}
		},
		"folder": {
			"name": "Chile/E-Deal"
		},
		"annotations": [],
		"type": "Parquet",
		"typeProperties": {
			"location": {
				"type": "AzureBlobFSLocation",
				"folderPath": {
					"value": "@dataset().file",
					"type": "Expression"
				},
				"fileSystem": {
					"value": "@dataset().zona",
					"type": "Expression"
				}
			},
			"compressionCodec": "none"
		},
		"schema": []
	},
	"type": "Microsoft.DataFactory/factories/datasets"
}